README.rst
setup.cfg
setup.py
Flask_Decorators.egg-info/PKG-INFO
Flask_Decorators.egg-info/SOURCES.txt
Flask_Decorators.egg-info/dependency_links.txt
Flask_Decorators.egg-info/not-zip-safe
Flask_Decorators.egg-info/pbr.json
Flask_Decorators.egg-info/requires.txt
Flask_Decorators.egg-info/top_level.txt
flask_decorators/__init__.py
flask_decorators/rest.py